ycct/__init__.py
ycct/client.py
ycct/command-map.toml
ycct/default.config.toml
ycct/functions.py
ycct/service.py
ycct/ycct.service
ycct-1.1.0.dist-info/licenses/LICENSE.md
ycct-1.1.0.dist-info/METADATA
ycct-1.1.0.dist-info/WHEEL
ycct-1.1.0.dist-info/entry_points.txt
ycct-1.1.0.dist-info/top_level.txt
ycct-1.1.0.dist-info/RECORD
