Metadata-Version: 2.4
Name: ycct
Version: 1.1.0
Summary: You Cant Change That - A File Monitoring and change prevention process
Author-email: AccidentallyTheCable <cableninja@cableninja.net>
License: GPLv3
Project-URL: Homepage, https://gitlab.com/accidentallythecable-public/python-modules/python-ycct/
Project-URL: Bug Tracker, https://gitlab.com/accidentallythecable-public/python-modules/python-ycct/issues
Classifier: Programming Language :: Python :: 3
Classifier: License :: OSI Approved :: GNU General Public License v3 (GPLv3)
Classifier: Environment :: Console
Classifier: Topic :: System :: Monitoring
Classifier: Topic :: System :: Logging
Classifier: Topic :: Utilities
Requires-Python: >=3.11
License-File: LICENSE.md
Requires-Dist: argstruct<2.0,>=1.0
Requires-Dist: atckit<2.0,>=1.0
Requires-Dist: argparser-ng<2.0,>=1.0
Dynamic: license-file
